fleaker/__init__.py
fleaker/_compat.py
fleaker/app.py
fleaker/base.py
fleaker/component.py
fleaker/config.py
fleaker/constants.py
fleaker/exceptions.py
fleaker/json.py
fleaker/logging.py
fleaker/missing.py
fleaker/orm.py
fleaker/test_client.py
fleaker/utils.py
fleaker/marshmallow/__init__.py
fleaker/marshmallow/constants.py
fleaker/marshmallow/extension.py
fleaker/marshmallow/json_schema.py
fleaker/marshmallow/schema.py
fleaker/marshmallow/fields/__init__.py
fleaker/marshmallow/fields/arrow.py
fleaker/marshmallow/fields/foreign_key.py
fleaker/marshmallow/fields/mixin.py
fleaker/marshmallow/fields/pendulum.py
fleaker/marshmallow/fields/phone_number.py
fleaker/peewee/__init__.py
fleaker/peewee/migrator.py
fleaker/peewee/model.py
fleaker/peewee/fields/__init__.py
fleaker/peewee/fields/arrow.py
fleaker/peewee/fields/json.py
fleaker/peewee/fields/pendulum.py
fleaker/peewee/mixins/__init__.py
fleaker/peewee/mixins/event.py
fleaker/peewee/mixins/field_signature.py
fleaker/peewee/mixins/search.py
fleaker/peewee/mixins/time/__init__.py
fleaker/peewee/mixins/time/arrow.py
fleaker/peewee/mixins/time/base.py
fleaker/peewee/mixins/time/pendulum.py
fleaker-0.4.0.dist-info/DESCRIPTION.rst
fleaker-0.4.0.dist-info/LICENSE.txt
fleaker-0.4.0.dist-info/METADATA
fleaker-0.4.0.dist-info/RECORD
fleaker-0.4.0.dist-info/WHEEL
fleaker-0.4.0.dist-info/metadata.json
fleaker-0.4.0.dist-info/top_level.txt
