Metadata-Version: 2.0
Name: fleaker
Version: 0.4.0
Summary: Tools and extensions to make Flask development easier.
Home-page: https://github.com/croscon/fleaker
Author: Croscon Consulting
Author-email: open.source@croscon.com
License: BSD
Download-URL: https://github.com/croscon/fleaker/archive/v0.4.0.tar.gz
Keywords: flask,web development,flask extension
Platform: any
Classifier: Development Status :: 2 - Pre-Alpha
Classifier: Environment :: Web Environment
Classifier: Framework :: Flask
Classifier: Intended Audience :: Developers
Classifier: License :: OSI Approved :: BSD License
Classifier: Operating System :: OS Independent
Classifier: Programming Language :: Python
Classifier: Programming Language :: Python :: 2
Classifier: Programming Language :: Python :: 3
Classifier: Topic :: Internet :: WWW/HTTP :: Dynamic Content
Classifier: Topic :: Software Development :: Libraries :: Application Frameworks
Classifier: Topic :: Software Development :: Libraries :: Python Modules
Requires-Dist: Flask
Requires-Dist: Flask-Classful
Requires-Dist: Flask-Login
Requires-Dist: Flask-Marshmallow
Requires-Dist: arrow
Requires-Dist: bcrypt
Requires-Dist: blinker
Requires-Dist: marshmallow
Requires-Dist: marshmallow-jsonschema
Requires-Dist: peewee
Requires-Dist: pendulum
Requires-Dist: phonenumbers
